LambdaALBRouter/__init__.py
LambdaALBRouter/exceptions.py
LambdaALBRouter/router.py
LambdaALBRouter/utils.py
LambdaALBRouter-0.2.dist-info/LICENSE
LambdaALBRouter-0.2.dist-info/METADATA
LambdaALBRouter-0.2.dist-info/WHEEL
LambdaALBRouter-0.2.dist-info/top_level.txt
LambdaALBRouter-0.2.dist-info/RECORD
