Metadata-Version: 2.1
Name: LambdaALBRouter
Version: 0.2
Summary: A package with flask-like syntax for routing requests from an AWS ALB in Lambda
Home-page: https://github.com/JeordyR/LambdaALBRouter
Author: Jeordy Rebbereh
Author-email: jeordy@gmail.com
License: UNKNOWN
Platform: UNKNOWN
Classifier: Programming Language :: Python :: 3.6
Classifier: Programming Language :: Python :: 3.7
Classifier: License :: OSI Approved :: MIT License
Classifier: Operating System :: OS Independent
Requires-Python: >=3.6
